LICENSE
README.md
setup.cfg
setup.py
odoo_version_manager/__init__.py
odoo_version_manager/config.py
odoo_version_manager/consts.py
odoo_version_manager/filelock.py
odoo_version_manager/gitcommands.py
odoo_version_manager/odoo_version_manager.py
odoo_version_manager/repo.py
odoo_version_manager/tools.py
odoo_version_manager.egg-info/PKG-INFO
odoo_version_manager.egg-info/SOURCES.txt
odoo_version_manager.egg-info/dependency_links.txt
odoo_version_manager.egg-info/entry_points.txt
odoo_version_manager.egg-info/requires.txt
odoo_version_manager.egg-info/top_level.txt