Metadata-Version: 2.1
Name: odoo-version-manager
Version: 0.0.20
Summary: Manage Versions of module along all odoo version
Home-page: https://github.com/odoo-module-version-manager.git
Author: Marc-Christian Wimmer
Author-email: marc@zebroo.de
License: MIT
Requires-Python: >=3.9.0
License-File: LICENSE
